README.rst
import_all.py
setup.cfg
setup.py
import_all.egg-info/PKG-INFO
import_all.egg-info/SOURCES.txt
import_all.egg-info/dependency_links.txt
import_all.egg-info/top_level.txt